{
  "main": {
    "id": "530eab11b88bd3db",
    "type": "split",
    "children": [
      {
        "id": "df4c1a7122f36096",
        "type": "tabs",
        "children": [
          {
            "id": "4ab80cc3f7dc06f6",
            "type": "leaf",
            "state": {
              "type": "markdown",
              "state": {
                "file": "knowledge-base/agents/index.md",
                "mode": "source",
                "source": false
              },
              "icon": "lucide-file",
              "title": "index"
            }
          }
        ]
      }
    ],
    "direction": "vertical"
  },
  "left": {
    "id": "80c6722602ab73e5",
    "type": "split",
    "children": [
      {
        "id": "ce37668c6916367c",
        "type": "tabs",
        "children": [
          {
            "id": "eb018de838d6e94d",
            "type": "leaf",
            "state": {
              "type": "file-explorer",
              "state": {
                "sortOrder": "alphabetical",
                "autoReveal": false
              },
              "icon": "lucide-folder-closed",
              "title": "Explorador de archivos"
            }
          },
          {
            "id": "c064e8ac5420baad",
            "type": "leaf",
            "state": {
              "type": "search",
              "state": {
                "query": "",
                "matchingCase": false,
                "explainSearch": false,
                "collapseAll": false,
                "extraContext": false,
                "sortOrder": "alphabetical"
              },
              "icon": "lucide-search",
              "title": "Buscar"
            }
          },
          {
            "id": "d55b911af24687c4",
            "type": "leaf",
            "state": {
              "type": "bookmarks",
              "state": {},
              "icon": "lucide-bookmark",
              "title": "Marcadores"
            }
          }
        ]
      }
    ],
    "direction": "horizontal",
    "width": 365.5
  },
  "right": {
    "id": "41d3d7bcba2d1fea",
    "type": "split",
    "children": [
      {
        "id": "176c80d9bb23bcd4",
        "type": "tabs",
        "children": [
          {
            "id": "e63dc52d7ac3b0bb",
            "type": "leaf",
            "state": {
              "type": "backlink",
              "state": {
                "file": "knowledge-base/guides/developer-environment-setup.md",
                "collapseAll": false,
                "extraContext": false,
                "sortOrder": "alphabetical",
                "showSearch": false,
                "searchQuery": "",
                "backlinkCollapsed": false,
                "unlinkedCollapsed": true
              },
              "icon": "links-coming-in",
              "title": "Enlaces entrantes de developer-environment-setup"
            }
          },
          {
            "id": "3551b47e87e340e6",
            "type": "leaf",
            "state": {
              "type": "outgoing-link",
              "state": {
                "file": "knowledge-base/guides/developer-environment-setup.md",
                "linksCollapsed": false,
                "unlinkedCollapsed": true
              },
              "icon": "links-going-out",
              "title": "Enlaces salientes de developer-environment-setup"
            }
          },
          {
            "id": "41dae7688e29c04b",
            "type": "leaf",
            "state": {
              "type": "tag",
              "state": {
                "sortOrder": "frequency",
                "useHierarchy": true,
                "showSearch": false,
                "searchQuery": ""
              },
              "icon": "lucide-tags",
              "title": "Etiquetas"
            }
          },
          {
            "id": "9ea4e9e757e35ed8",
            "type": "leaf",
            "state": {
              "type": "all-properties",
              "state": {
                "sortOrder": "frequency",
                "showSearch": false,
                "searchQuery": ""
              },
              "icon": "lucide-archive",
              "title": "Todas las propiedades"
            }
          },
          {
            "id": "7a7b11a9c6612a93",
            "type": "leaf",
            "state": {
              "type": "outline",
              "state": {
                "file": "knowledge-base/guides/developer-environment-setup.md",
                "followCursor": false,
                "showSearch": false,
                "searchQuery": ""
              },
              "icon": "lucide-list",
              "title": "Esquema de developer-environment-setup"
            }
          }
        ]
      }
    ],
    "direction": "horizontal",
    "width": 300,
    "collapsed": true
  },
  "left-ribbon": {
    "hiddenItems": {
      "switcher:Abrir selector rápido": false,
      "graph:Abrir vista gráfica": false,
      "canvas:Crear nuevo lienzo": false,
      "daily-notes:Abrir la nota de hoy": false,
      "templates:Insertar plantilla": false,
      "command-palette:Abrir paleta de comandos": false,
      "bases:Crear nueva base": false
    }
  },
  "active": "4ab80cc3f7dc06f6",
  "lastOpenFiles": [
    "knowledge-base/agents/product-owner.agent.md",
    "knowledge-base/agents/index.md",
    "knowledge-base/agents/frontend-developer.agent.md",
    "knowledge-base/agents/backend-developer.agent.md",
    "Universidad de palermo/Lenguajes Automatas y Finitos/Apuntes/M2.2 - Clasificacion de Gramaticas.md",
    "knowledge-base/prompts/write-tasks.prompt.md",
    "knowledge-base/prompts/write-spec.prompt.md",
    "knowledge-base/prompts/write-plan.prompt.md",
    "knowledge-base/prompts/load-feature.prompt.md",
    "knowledge-base/prompts/implement.prompt.md",
    "knowledge-base/prompts/eod.prompt.md",
    "knowledge-base/instructions/spec-writing.md",
    "knowledge-base/instructions/load-feature.md",
    "knowledge-base/instructions/eod-instructions.md",
    "knowledge-base/Improvements to be made.md",
    "knowledge-base/bruno/Signals/Users/Get User BY Id.yml",
    "knowledge-base/bruno/Signals/Users/folder.yml",
    "knowledge-base/bruno/Signals/opencollection.yml",
    "knowledge-base/bruno/Signals/environments/Signals - Stage.yml",
    "knowledge-base/bruno/Signals/environments/Signals - Prod.yml",
    "knowledge-base/bruno/Signals/environments/Signals - Dev.yml",
    "knowledge-base/bruno/Signals/Entities/Uptade ADO.yml",
    "knowledge-base/bruno/Signals/Entities/Templates/folder.yml",
    "knowledge-base/bruno/Signals/Entities/Templates/entities-templates-eid-fields.yml",
    "knowledge-base/bruno/Signals/Entities/Search/folder.yml",
    "knowledge-base/applications/tracker/features/automation-testing-AB#2266524/tasks.md",
    "knowledge-base/applications/tracker/features/automation-testing-AB#2266524/specs.md",
    "knowledge-base/applications/tracker/features/automation-testing-AB#2266524/proposal.md",
    "knowledge-base/applications/tracker/features/automation-testing-AB#2266524/plan.md",
    "knowledge-base/applications/tracker/features/automation-testing-AB#2266524/Instructions.md",
    "knowledge-base/applications/tracker/features/automation-testing-AB#2266524/Contexts/2026-04-17_1700-latest.md",
    "knowledge-base/applications/tracker/features/automation-testing-AB#2266524/Contexts/2026-04-16_1430.md",
    "knowledge-base/applications/helper-service/General Information.md",
    "knowledge-base/applications/helper-service/features/watson-study-metrics-AB#2271880/tasks.md",
    "knowledge-base/applications/helper-service/features/watson-study-metrics-AB#2271880/spec.md",
    "knowledge-base/applications/helper-service/features/watson-study-metrics-AB#2271880/proposal.md"
  ]
}